GenomeUtils/Downloaders.py
GenomeUtils/Genome.py
GenomeUtils/__init__.py
GenomeUtils/downloaders/__init__.py
GenomeUtils/downloaders/downloader.py
GenomeUtils/downloaders/genome_downloader.py
GenomeUtils/genome/__init__.py
GenomeUtils/genome/builder.py
GenomeUtils/genome/chromosome.py
GenomeUtils/genome/exon.py
GenomeUtils/genome/gene.py
GenomeUtils/genome/genome.py
GenomeUtils/genome/genome_element.py
GenomeUtils/genome/locus.py
GenomeUtils/genome/transcript.py
genomeutils-0.1.1.dist-info/licenses/COPYING
genomeutils-0.1.1.dist-info/licenses/COPYING.LESSER
genomeutils-0.1.1.dist-info/METADATA
genomeutils-0.1.1.dist-info/WHEEL
genomeutils-0.1.1.dist-info/top_level.txt
genomeutils-0.1.1.dist-info/RECORD
