Metadata-Version: 2.4
Name: GenomeUtils
Version: 0.1.1
Summary: An object-oriented Python library for working with genomic data.
Author-email: Seyedarash Ayatollahi <seyedarash.ayatollahi@b-tu.de>
Maintainer-email: Nathalie Gocht <nathalie.gocht@b-tu.de>
License-Expression: LGPL-3.0-or-later
Classifier: Programming Language :: Python :: 3
Classifier: Programming Language :: Python :: 3.10
Classifier: Operating System :: OS Independent
Requires-Python: >=3.10
License-File: COPYING
License-File: COPYING.LESSER
Requires-Dist: gffutils<0.14,>=0.13
Requires-Dist: requests<3,>=2.32
Requires-Dist: biopython<2,>=1.83
Requires-Dist: gget<0.30,>=0.29
Requires-Dist: tqdm<5,>=4.67
Dynamic: license-file
